scm_wrap-1.2.0.dist-info/licenses/LICENSE
scmwrap/__init__.py
scmwrap/git.py
scmwrap/py.typed
scmwrap/repo.py
scmwrap/scmwrap.py
scmwrap/svn.py
scm_wrap-1.2.0.dist-info/METADATA
scm_wrap-1.2.0.dist-info/WHEEL
scm_wrap-1.2.0.dist-info/top_level.txt
scm_wrap-1.2.0.dist-info/RECORD
