Metadata-Version: 2.4
Name: scm-wrap
Version: 1.2.0
Summary: Source Code Management module wrapper. This module aims to wrap access to Git, Subversion and other SCMs repositories
Author-email: Marco Bascetta <m.bascetta@zohomail.eu>, Matteo Martelli <matteomartelli3@gmail.com>, Marco Melletti <melletti.marco@gmail.com>
Classifier: Programming Language :: Python :: 3
Classifier: Operating System :: OS Independent
Requires-Python: >=3.7
License-File: LICENSE
Requires-Dist: bpython==0.21
Requires-Dist: pyinstaller==4.5.1
Requires-Dist: argcomplete
Requires-Dist: wcwidth
Requires-Dist: bs4
Requires-Dist: lxml
Requires-Dist: rich
Dynamic: license-file
